{"modelCheckResultList":[{"backwardTransitions":[],"probability":0.1,"expectedMessages":2.0,"id":0,"epochTimestamp":1658429294574},{"backwardTransitions":[[0,-1]],"probability":0.1369862808089541,"expectedMessages":2.7397245043669685,"id":1308927845,"epochTimestamp":1658429294574},{"backwardTransitions":[[1,-1]],"probability":0.07216489,"expectedMessages":2.06185481,"id":2017354584,"epochTimestamp":1658429294574},{"backwardTransitions":[[-1,-1]],"probability":1.0,"expectedMessages":20.0,"id":391447681,"epochTimestamp":1658429294574},{"backwardTransitions":[[0,-1],[1,-1]],"probability":0.09999998405676999,"expectedMessages":2.85714133874,"id":-968684867,"epochTimestamp":1658429294574},{"backwardTransitions":[[0,-1],[-1,-1]],"probability":1.0,"expectedMessages":20.0,"id":1700375526,"epochTimestamp":1658429294574},{"backwardTransitions":[[-1,-1],[1,-1]],"probability":1.0,"expectedMessages":28.571413918841007,"id":-1886165031,"epochTimestamp":1658429294574},{"backwardTransitions":[[0,-1],[-1,-1],[1,-1]],"probability":1.0,"expectedMessages":28.571413918841007,"id":-577237186,"epochTimestamp":1658429294574}],"specification":[[1,1],[1,0],[1,1]],"organizations":["Org1","Org2"]}